aysclient
