Metadata-Version: 1.1
Name: aysclient
Version: 0.0.4
Summary: AtYourService client (AYS)
Home-page: https://github.com/Jumpscale/ays9/tree/master/clients/sync_client
Author: Ahmed T. Youssef
Author-email: xmonader@gmail.com
License: Apache
Platform: UNKNOWN
Classifier: Development Status :: 5 - Production/Stable
Classifier: Intended Audience :: Developers
Classifier: License :: OSI Approved :: Apache Software License
Classifier: Operating System :: MacOS :: MacOS X
Classifier: Operating System :: Microsoft :: Windows
Classifier: Operating System :: POSIX
Classifier: Programming Language :: Python
